README.md
setup.py
poloniex/__init__.py
poloniex/coach.py
poloniexapi.egg-info/PKG-INFO
poloniexapi.egg-info/SOURCES.txt
poloniexapi.egg-info/dependency_links.txt
poloniexapi.egg-info/not-zip-safe
poloniexapi.egg-info/requires.txt
poloniexapi.egg-info/top_level.txt