Metadata-Version: 2.1
Name: poloniexapi
Version: 0.5.5
Summary: Poloniex API wrapper for Python 2.7 and 3 with websocket support
Home-page: https://github.com/s4w3d0ff/python-poloniex
Author: s4w3d0ff
Author-email: info@s4w3d0ff.host
License: GPL v2
Keywords: poloniex,poloniexapi,exchange,api,cryptocoin,tradebot,polo,websocket,rest,push
Platform: UNKNOWN
Classifier: Operating System :: MacOS :: MacOS X
Classifier: Operating System :: Microsoft :: Windows
Classifier: Operating System :: POSIX
Classifier: License :: OSI Approved :: GNU General Public License v2 (GPLv2)
Classifier: Programming Language :: Python :: 2
Classifier: Programming Language :: Python :: 3
